{"_ts":[1546312483,1546357029],"_r":{"breakdown":{"html":{"bytes":[1252,1253],"requests":[10,10]},"js":{"bytes":[486492,486067],"requests":[17,17]},"css":{"bytes":[18995,19003],"requests":[2,2]},"image":{"bytes":[16730,16877],"requests":[27,27]},"flash":{"bytes":[0,0],"requests":[0,0]},"font":{"bytes":[47741,47741],"requests":[3,3]},"video":{"bytes":[0,0],"requests":[0,0]},"other":{"bytes":[7724,7726],"requests":[3,3]}},"date":[1546312483,1546357029],"domElements":[99,99],"domInteractive":[1053.3333333333333,963.6666666666666],"firstPaint":[401.1000000003333,315.1666666663],"fullyLoaded":[3703,3529],"id":["190101_N5_f8ef0ba674fa0dc84629caa8655b0dbf","190101_51_292f51f09eee10d26780631cb181e647"],"loadTime":[1053.6666666666667,964.3333333333334],"render":[400,300],"SpeedIndex":[1256.3333333333333,1123],"TTFB":[302.6666666666667,213.66666666666666],"videoFrames":[[{"_i":"ms_000000.jpg","_t":0,"_vc":0},{"_i":"ms_000400.jpg","_t":400,"_vc":3},{"_i":"ms_000500.jpg","_t":500,"_vc":3},{"_i":"ms_000600.jpg","_t":600,"_vc":3},{"_i":"ms_000700.jpg","_t":700,"_vc":3},{"_i":"ms_000800.jpg","_t":800,"_vc":3},{"_i":"ms_000900.jpg","_t":900,"_vc":3},{"_i":"ms_001000.jpg","_t":1000,"_vc":3},{"_i":"ms_001100.jpg","_t":1100,"_vc":0},{"_i":"ms_001200.jpg","_t":1200,"_vc":98},{"_i":"ms_001300.jpg","_t":1300,"_vc":82},{"_i":"ms_001400.jpg","_t":1400,"_vc":84},{"_i":"ms_001500.jpg","_t":1500,"_vc":100}],[{"_i":"ms_000000.jpg","_t":0,"_vc":0},{"_i":"ms_000400.jpg","_t":400,"_vc":3},{"_i":"ms_000500.jpg","_t":500,"_vc":3},{"_i":"ms_000600.jpg","_t":600,"_vc":3},{"_i":"ms_000700.jpg","_t":700,"_vc":3},{"_i":"ms_000800.jpg","_t":800,"_vc":3},{"_i":"ms_000900.jpg","_t":900,"_vc":3},{"_i":"ms_001000.jpg","_t":1000,"_vc":2},{"_i":"ms_001100.jpg","_t":1100,"_vc":0},{"_i":"ms_001200.jpg","_t":1200,"_vc":93},{"_i":"ms_001300.jpg","_t":1300,"_vc":84},{"_i":"ms_001500.jpg","_t":1500,"_vc":96},{"_i":"ms_001600.jpg","_t":1600,"_vc":100}]],"visualComplete":[1566.6666666666667,1500],"lighthouse":[46,46],"pagespeed":[76,76]}}