{"_ts":[1559377675],"_r":{"breakdown":{"html":{"bytes":[46101],"requests":[10]},"js":{"bytes":[813450],"requests":[35]},"css":{"bytes":[7998],"requests":[2]},"image":{"bytes":[126376],"requests":[55]},"flash":{"bytes":[0],"requests":[0]},"font":{"bytes":[77696],"requests":[6]},"video":{"bytes":[0],"requests":[0]},"other":{"bytes":[1009783],"requests":[22]}},"date":[1559377675],"domElements":[1241.6666666666667],"domInteractive":[1100.6666666666667],"firstPaint":[1332.3666666656334],"fullyLoaded":[15336.333333333334],"id":["190601_SH_e42cc6992c97726ae2ef2578287abc1d"],"loadTime":[11412.666666666666],"render":[1333.3333333333333],"SpeedIndex":[2415.6666666666665],"TTFB":[460.3333333333333],"videoFrames":[[{"_i":"ms_000000.jpg","_t":0,"_vc":0},{"_i":"ms_001500.jpg","_t":1500,"_vc":72},{"_i":"ms_002100.jpg","_t":2100,"_vc":74},{"_i":"ms_004200.jpg","_t":4200,"_vc":59},{"_i":"ms_004600.jpg","_t":4600,"_vc":97},{"_i":"ms_004900.jpg","_t":4900,"_vc":97},{"_i":"ms_005700.jpg","_t":5700,"_vc":98},{"_i":"ms_005900.jpg","_t":5900,"_vc":98},{"_i":"ms_006400.jpg","_t":6400,"_vc":97},{"_i":"ms_006700.jpg","_t":6700,"_vc":98},{"_i":"ms_006900.jpg","_t":6900,"_vc":98},{"_i":"ms_007300.jpg","_t":7300,"_vc":98},{"_i":"ms_007500.jpg","_t":7500,"_vc":98},{"_i":"ms_008200.jpg","_t":8200,"_vc":98},{"_i":"ms_008800.jpg","_t":8800,"_vc":100},{"_i":"ms_009700.jpg","_t":9700,"_vc":100},{"_i":"ms_009800.jpg","_t":9800,"_vc":100},{"_i":"ms_010400.jpg","_t":10400,"_vc":100},{"_i":"ms_010501.jpg","_t":10501,"_vc":100},{"_i":"ms_012100.jpg","_t":12100,"_vc":100},{"_i":"ms_012700.jpg","_t":12700,"_vc":100},{"_i":"ms_013200.jpg","_t":13200,"_vc":100},{"_i":"ms_013500.jpg","_t":13500,"_vc":100},{"_i":"ms_014100.jpg","_t":14100,"_vc":100},{"_i":"ms_014600.jpg","_t":14600,"_vc":100},{"_i":"ms_015000.jpg","_t":15000,"_vc":100},{"_i":"ms_015100.jpg","_t":15100,"_vc":100}]],"visualComplete":[8900],"lighthouse":[30],"pagespeed":[88]}}